modelarchive/__init__.py
modelarchive/archive.py
modelarchive/helpers.py
modelarchive-0.0.1.dev7.dist-info/AUTHORS
modelarchive-0.0.1.dev7.dist-info/LICENSE
modelarchive-0.0.1.dev7.dist-info/METADATA
modelarchive-0.0.1.dev7.dist-info/WHEEL
modelarchive-0.0.1.dev7.dist-info/pbr.json
modelarchive-0.0.1.dev7.dist-info/top_level.txt
modelarchive-0.0.1.dev7.dist-info/RECORD
