Metadata-Version: 2.1
Name: modelarchive
Version: 0.0.1.dev7
Summary: UNKNOWN
Home-page: https://github.com/seung-lab/modelarchive
Author: Barak Nehoran
Author-email: bnehoran@users.noreply.github.com
License: BSD
Platform: UNKNOWN
Classifier: Intended Audience :: Developers
Classifier: Development Status :: 4 - Beta
Classifier: Programming Language :: Python :: 3
Classifier: Programming Language :: Python :: 3.5
Classifier: Programming Language :: Python :: 3.6
Classifier: Programming Language :: Python :: 3.7
Classifier: Topic :: Scientific/Engineering
Classifier: License :: OSI Approved :: MIT License
Requires-Dist: torch (>=0.4.1)
Requires-Dist: torchvision
Requires-Dist: numpy
Requires-Dist: matplotlib
Requires-Dist: h5py
Requires-Dist: argcomplete
Requires-Dist: pandas
Requires-Dist: setuptools
Requires-Dist: pyyaml
